envdo/__init__.py
envdo/cli.py
envdo/utils.py
envdo-0.1.3.dist-info/licenses/LICENSE
envdo-0.1.3.dist-info/METADATA
envdo-0.1.3.dist-info/WHEEL
envdo-0.1.3.dist-info/entry_points.txt
envdo-0.1.3.dist-info/top_level.txt
envdo-0.1.3.dist-info/RECORD
