Metadata-Version: 2.4
Name: envdo
Version: 0.1.3
Summary: 为命令行程序配置临时的启动环境变量，特别适合为 claude code 配置切换模型。
Project-URL: repository, https://github.com/NewToolAI/envdo
Requires-Python: >=3.8
License-File: LICENSE
Requires-Dist: rich>=14.2.0
Dynamic: license-file
